{
  "date": "2018-06-11",
  "market": "OMIE Portugal day-ahead",
  "rows": [
    {
      "x": 1528675200000,
      "price": 56.47
    },
    {
      "x": 1528678800000,
      "price": 54.9
    },
    {
      "x": 1528682400000,
      "price": 51.43
    },
    {
      "x": 1528686000000,
      "price": 51.43
    },
    {
      "x": 1528689600000,
      "price": 51.07
    },
    {
      "x": 1528693200000,
      "price": 51.67
    },
    {
      "x": 1528696800000,
      "price": 57.12
    },
    {
      "x": 1528700400000,
      "price": 59.0
    },
    {
      "x": 1528704000000,
      "price": 62.17
    },
    {
      "x": 1528707600000,
      "price": 63.04
    },
    {
      "x": 1528711200000,
      "price": 63.24
    },
    {
      "x": 1528714800000,
      "price": 63.44
    },
    {
      "x": 1528718400000,
      "price": 63.24
    },
    {
      "x": 1528722000000,
      "price": 63.04
    },
    {
      "x": 1528725600000,
      "price": 62.1
    },
    {
      "x": 1528729200000,
      "price": 60.87
    },
    {
      "x": 1528732800000,
      "price": 60.51
    },
    {
      "x": 1528736400000,
      "price": 60.2
    },
    {
      "x": 1528740000000,
      "price": 59.62
    },
    {
      "x": 1528743600000,
      "price": 59.09
    },
    {
      "x": 1528747200000,
      "price": 60.51
    },
    {
      "x": 1528750800000,
      "price": 62.78
    },
    {
      "x": 1528754400000,
      "price": 60.59
    },
    {
      "x": 1528758000000,
      "price": 58.37
    }
  ]
}