{
  "date": "2019-05-22",
  "market": "OMIE Portugal day-ahead",
  "rows": [
    {
      "x": 1558483200000,
      "price": 59.27
    },
    {
      "x": 1558486800000,
      "price": 59.27
    },
    {
      "x": 1558490400000,
      "price": 58.73
    },
    {
      "x": 1558494000000,
      "price": 58.73
    },
    {
      "x": 1558497600000,
      "price": 58.9
    },
    {
      "x": 1558501200000,
      "price": 59.47
    },
    {
      "x": 1558504800000,
      "price": 59.39
    },
    {
      "x": 1558508400000,
      "price": 57.21
    },
    {
      "x": 1558512000000,
      "price": 58.7
    },
    {
      "x": 1558515600000,
      "price": 58.68
    },
    {
      "x": 1558519200000,
      "price": 58.35
    },
    {
      "x": 1558522800000,
      "price": 58.1
    },
    {
      "x": 1558526400000,
      "price": 58.73
    },
    {
      "x": 1558530000000,
      "price": 58.55
    },
    {
      "x": 1558533600000,
      "price": 57.02
    },
    {
      "x": 1558537200000,
      "price": 56.5
    },
    {
      "x": 1558540800000,
      "price": 56.02
    },
    {
      "x": 1558544400000,
      "price": 56.4
    },
    {
      "x": 1558548000000,
      "price": 55.68
    },
    {
      "x": 1558551600000,
      "price": 55.56
    },
    {
      "x": 1558555200000,
      "price": 57.03
    },
    {
      "x": 1558558800000,
      "price": 59.21
    },
    {
      "x": 1558562400000,
      "price": 58.01
    },
    {
      "x": 1558566000000,
      "price": 58.13
    }
  ]
}