{
  "date": "2020-02-22",
  "market": "OMIE Portugal day-ahead",
  "rows": [
    {
      "x": 1582329600000,
      "price": 42.02
    },
    {
      "x": 1582333200000,
      "price": 40.12
    },
    {
      "x": 1582336800000,
      "price": 38.35
    },
    {
      "x": 1582340400000,
      "price": 38.5
    },
    {
      "x": 1582344000000,
      "price": 38.35
    },
    {
      "x": 1582347600000,
      "price": 38.51
    },
    {
      "x": 1582351200000,
      "price": 37.29
    },
    {
      "x": 1582354800000,
      "price": 38.1
    },
    {
      "x": 1582358400000,
      "price": 39.1
    },
    {
      "x": 1582362000000,
      "price": 39.42
    },
    {
      "x": 1582365600000,
      "price": 39.96
    },
    {
      "x": 1582369200000,
      "price": 39.0
    },
    {
      "x": 1582372800000,
      "price": 38.01
    },
    {
      "x": 1582376400000,
      "price": 37.85
    },
    {
      "x": 1582380000000,
      "price": 37.47
    },
    {
      "x": 1582383600000,
      "price": 36.85
    },
    {
      "x": 1582387200000,
      "price": 36.85
    },
    {
      "x": 1582390800000,
      "price": 37.9
    },
    {
      "x": 1582394400000,
      "price": 39.59
    },
    {
      "x": 1582398000000,
      "price": 44.51
    },
    {
      "x": 1582401600000,
      "price": 46.5
    },
    {
      "x": 1582405200000,
      "price": 45.01
    },
    {
      "x": 1582408800000,
      "price": 42.6
    },
    {
      "x": 1582412400000,
      "price": 41.5
    }
  ]
}