{
  "date": "2020-03-05",
  "market": "OMIE Portugal day-ahead",
  "rows": [
    {
      "x": 1583366400000,
      "price": 27.85
    },
    {
      "x": 1583370000000,
      "price": 24.8
    },
    {
      "x": 1583373600000,
      "price": 22.05
    },
    {
      "x": 1583377200000,
      "price": 22.05
    },
    {
      "x": 1583380800000,
      "price": 21.41
    },
    {
      "x": 1583384400000,
      "price": 22.0
    },
    {
      "x": 1583388000000,
      "price": 23.8
    },
    {
      "x": 1583391600000,
      "price": 26.3
    },
    {
      "x": 1583395200000,
      "price": 28.51
    },
    {
      "x": 1583398800000,
      "price": 28.95
    },
    {
      "x": 1583402400000,
      "price": 28.35
    },
    {
      "x": 1583406000000,
      "price": 26.0
    },
    {
      "x": 1583409600000,
      "price": 25.3
    },
    {
      "x": 1583413200000,
      "price": 24.3
    },
    {
      "x": 1583416800000,
      "price": 22.05
    },
    {
      "x": 1583420400000,
      "price": 21.99
    },
    {
      "x": 1583424000000,
      "price": 21.9
    },
    {
      "x": 1583427600000,
      "price": 23.03
    },
    {
      "x": 1583431200000,
      "price": 24.35
    },
    {
      "x": 1583434800000,
      "price": 28.35
    },
    {
      "x": 1583438400000,
      "price": 30.24
    },
    {
      "x": 1583442000000,
      "price": 27.85
    },
    {
      "x": 1583445600000,
      "price": 26.9
    },
    {
      "x": 1583449200000,
      "price": 25.3
    }
  ]
}