{
  "date": "2020-07-03",
  "market": "OMIE Portugal day-ahead",
  "rows": [
    {
      "x": 1593734400000,
      "price": 37.87
    },
    {
      "x": 1593738000000,
      "price": 33.99
    },
    {
      "x": 1593741600000,
      "price": 29.02
    },
    {
      "x": 1593745200000,
      "price": 27.62
    },
    {
      "x": 1593748800000,
      "price": 29.02
    },
    {
      "x": 1593752400000,
      "price": 29.86
    },
    {
      "x": 1593756000000,
      "price": 35.87
    },
    {
      "x": 1593759600000,
      "price": 38.87
    },
    {
      "x": 1593763200000,
      "price": 38.74
    },
    {
      "x": 1593766800000,
      "price": 38.95
    },
    {
      "x": 1593770400000,
      "price": 38.95
    },
    {
      "x": 1593774000000,
      "price": 38.18
    },
    {
      "x": 1593777600000,
      "price": 37.49
    },
    {
      "x": 1593781200000,
      "price": 37.87
    },
    {
      "x": 1593784800000,
      "price": 35.05
    },
    {
      "x": 1593788400000,
      "price": 31.72
    },
    {
      "x": 1593792000000,
      "price": 30.47
    },
    {
      "x": 1593795600000,
      "price": 32.3
    },
    {
      "x": 1593799200000,
      "price": 37.29
    },
    {
      "x": 1593802800000,
      "price": 38.87
    },
    {
      "x": 1593806400000,
      "price": 37.02
    },
    {
      "x": 1593810000000,
      "price": 35.3
    },
    {
      "x": 1593813600000,
      "price": 36.15
    },
    {
      "x": 1593817200000,
      "price": 31.49
    }
  ]
}