{
  "date": "2020-02-07",
  "market": "OMIE Portugal day-ahead",
  "rows": [
    {
      "x": 1581033600000,
      "price": 41.21
    },
    {
      "x": 1581037200000,
      "price": 37.05
    },
    {
      "x": 1581040800000,
      "price": 32.19
    },
    {
      "x": 1581044400000,
      "price": 30.55
    },
    {
      "x": 1581048000000,
      "price": 30.55
    },
    {
      "x": 1581051600000,
      "price": 35.55
    },
    {
      "x": 1581055200000,
      "price": 40.09
    },
    {
      "x": 1581058800000,
      "price": 44.8
    },
    {
      "x": 1581062400000,
      "price": 48.11
    },
    {
      "x": 1581066000000,
      "price": 47.0
    },
    {
      "x": 1581069600000,
      "price": 43.01
    },
    {
      "x": 1581073200000,
      "price": 41.75
    },
    {
      "x": 1581076800000,
      "price": 40.5
    },
    {
      "x": 1581080400000,
      "price": 38.88
    },
    {
      "x": 1581084000000,
      "price": 37.7
    },
    {
      "x": 1581087600000,
      "price": 36.55
    },
    {
      "x": 1581091200000,
      "price": 37.51
    },
    {
      "x": 1581094800000,
      "price": 40.0
    },
    {
      "x": 1581098400000,
      "price": 42.08
    },
    {
      "x": 1581102000000,
      "price": 44.0
    },
    {
      "x": 1581105600000,
      "price": 44.01
    },
    {
      "x": 1581109200000,
      "price": 43.27
    },
    {
      "x": 1581112800000,
      "price": 41.75
    },
    {
      "x": 1581116400000,
      "price": 38.84
    }
  ]
}