{
  "date": "2020-10-31",
  "market": "OMIE Portugal day-ahead",
  "rows": [
    {
      "x": 1604102400000,
      "price": 35.04
    },
    {
      "x": 1604106000000,
      "price": 34.02
    },
    {
      "x": 1604109600000,
      "price": 30.0
    },
    {
      "x": 1604113200000,
      "price": 30.03
    },
    {
      "x": 1604116800000,
      "price": 33.59
    },
    {
      "x": 1604120400000,
      "price": 33.35
    },
    {
      "x": 1604124000000,
      "price": 34.01
    },
    {
      "x": 1604127600000,
      "price": 35.33
    },
    {
      "x": 1604131200000,
      "price": 36.94
    },
    {
      "x": 1604134800000,
      "price": 38.74
    },
    {
      "x": 1604138400000,
      "price": 36.6
    },
    {
      "x": 1604142000000,
      "price": 34.19
    },
    {
      "x": 1604145600000,
      "price": 34.0
    },
    {
      "x": 1604149200000,
      "price": 34.0
    },
    {
      "x": 1604152800000,
      "price": 30.0
    },
    {
      "x": 1604156400000,
      "price": 28.8
    },
    {
      "x": 1604160000000,
      "price": 29.9
    },
    {
      "x": 1604163600000,
      "price": 38.25
    },
    {
      "x": 1604167200000,
      "price": 39.95
    },
    {
      "x": 1604170800000,
      "price": 41.45
    },
    {
      "x": 1604174400000,
      "price": 44.83
    },
    {
      "x": 1604178000000,
      "price": 44.82
    },
    {
      "x": 1604181600000,
      "price": 40.9
    },
    {
      "x": 1604185200000,
      "price": 39.75
    }
  ]
}