{
  "date": "2021-10-17",
  "market": "OMIE Portugal day-ahead",
  "rows": [
    {
      "x": 1634428800000,
      "price": 216.2
    },
    {
      "x": 1634432400000,
      "price": 208.81
    },
    {
      "x": 1634436000000,
      "price": 198.41
    },
    {
      "x": 1634439600000,
      "price": 192.03
    },
    {
      "x": 1634443200000,
      "price": 190.05
    },
    {
      "x": 1634446800000,
      "price": 189.39
    },
    {
      "x": 1634450400000,
      "price": 186.27
    },
    {
      "x": 1634454000000,
      "price": 198.61
    },
    {
      "x": 1634457600000,
      "price": 198.41
    },
    {
      "x": 1634461200000,
      "price": 203.56
    },
    {
      "x": 1634464800000,
      "price": 198.71
    },
    {
      "x": 1634468400000,
      "price": 198.41
    },
    {
      "x": 1634472000000,
      "price": 198.41
    },
    {
      "x": 1634475600000,
      "price": 198.41
    },
    {
      "x": 1634479200000,
      "price": 197.24
    },
    {
      "x": 1634482800000,
      "price": 184.71
    },
    {
      "x": 1634486400000,
      "price": 183.84
    },
    {
      "x": 1634490000000,
      "price": 191.91
    },
    {
      "x": 1634493600000,
      "price": 216.0
    },
    {
      "x": 1634497200000,
      "price": 250.0
    },
    {
      "x": 1634500800000,
      "price": 270.0
    },
    {
      "x": 1634504400000,
      "price": 264.54
    },
    {
      "x": 1634508000000,
      "price": 252.88
    },
    {
      "x": 1634511600000,
      "price": 244.21
    }
  ]
}