{
  "date": "2022-12-01",
  "market": "OMIE Portugal day-ahead",
  "rows": [
    {
      "x": 1669852800000,
      "price": 151.84
    },
    {
      "x": 1669856400000,
      "price": 132.22
    },
    {
      "x": 1669860000000,
      "price": 134.26
    },
    {
      "x": 1669863600000,
      "price": 134.26
    },
    {
      "x": 1669867200000,
      "price": 123.41
    },
    {
      "x": 1669870800000,
      "price": 131.01
    },
    {
      "x": 1669874400000,
      "price": 145.0
    },
    {
      "x": 1669878000000,
      "price": 152.42
    },
    {
      "x": 1669881600000,
      "price": 162.14
    },
    {
      "x": 1669885200000,
      "price": 161.0
    },
    {
      "x": 1669888800000,
      "price": 148.42
    },
    {
      "x": 1669892400000,
      "price": 148.0
    },
    {
      "x": 1669896000000,
      "price": 147.0
    },
    {
      "x": 1669899600000,
      "price": 153.38
    },
    {
      "x": 1669903200000,
      "price": 151.06
    },
    {
      "x": 1669906800000,
      "price": 151.84
    },
    {
      "x": 1669910400000,
      "price": 147.21
    },
    {
      "x": 1669914000000,
      "price": 161.44
    },
    {
      "x": 1669917600000,
      "price": 168.14
    },
    {
      "x": 1669921200000,
      "price": 172.32
    },
    {
      "x": 1669924800000,
      "price": 175.8
    },
    {
      "x": 1669928400000,
      "price": 164.34
    },
    {
      "x": 1669932000000,
      "price": 151.03
    },
    {
      "x": 1669935600000,
      "price": 134.26
    }
  ]
}