{
  "date": "2023-11-02",
  "market": "OMIE Portugal day-ahead",
  "rows": [
    {
      "x": 1698883200000,
      "price": 4.3
    },
    {
      "x": 1698886800000,
      "price": 4.3
    },
    {
      "x": 1698890400000,
      "price": 0.77
    },
    {
      "x": 1698894000000,
      "price": 0.06
    },
    {
      "x": 1698897600000,
      "price": 0.09
    },
    {
      "x": 1698901200000,
      "price": 1.6
    },
    {
      "x": 1698904800000,
      "price": 4.3
    },
    {
      "x": 1698908400000,
      "price": 5.0
    },
    {
      "x": 1698912000000,
      "price": 10.0
    },
    {
      "x": 1698915600000,
      "price": 4.55
    },
    {
      "x": 1698919200000,
      "price": 4.3
    },
    {
      "x": 1698922800000,
      "price": 4.3
    },
    {
      "x": 1698926400000,
      "price": 4.3
    },
    {
      "x": 1698930000000,
      "price": 4.3
    },
    {
      "x": 1698933600000,
      "price": 4.3
    },
    {
      "x": 1698937200000,
      "price": 3.8
    },
    {
      "x": 1698940800000,
      "price": 4.3
    },
    {
      "x": 1698944400000,
      "price": 4.3
    },
    {
      "x": 1698948000000,
      "price": 4.5
    },
    {
      "x": 1698951600000,
      "price": 10.0
    },
    {
      "x": 1698955200000,
      "price": 10.0
    },
    {
      "x": 1698958800000,
      "price": 4.55
    },
    {
      "x": 1698962400000,
      "price": 4.3
    },
    {
      "x": 1698966000000,
      "price": 3.8
    }
  ]
}