{
  "date": "2023-06-14",
  "market": "OMIE Portugal day-ahead",
  "rows": [
    {
      "x": 1686700800000,
      "price": 96.28
    },
    {
      "x": 1686704400000,
      "price": 88.68
    },
    {
      "x": 1686708000000,
      "price": 86.98
    },
    {
      "x": 1686711600000,
      "price": 86.25
    },
    {
      "x": 1686715200000,
      "price": 85.83
    },
    {
      "x": 1686718800000,
      "price": 93.43
    },
    {
      "x": 1686722400000,
      "price": 97.72
    },
    {
      "x": 1686726000000,
      "price": 99.75
    },
    {
      "x": 1686729600000,
      "price": 85.0
    },
    {
      "x": 1686733200000,
      "price": 69.0
    },
    {
      "x": 1686736800000,
      "price": 66.17
    },
    {
      "x": 1686740400000,
      "price": 55.07
    },
    {
      "x": 1686744000000,
      "price": 65.5
    },
    {
      "x": 1686747600000,
      "price": 67.99
    },
    {
      "x": 1686751200000,
      "price": 67.77
    },
    {
      "x": 1686754800000,
      "price": 68.07
    },
    {
      "x": 1686758400000,
      "price": 68.07
    },
    {
      "x": 1686762000000,
      "price": 71.22
    },
    {
      "x": 1686765600000,
      "price": 75.92
    },
    {
      "x": 1686769200000,
      "price": 97.79
    },
    {
      "x": 1686772800000,
      "price": 102.37
    },
    {
      "x": 1686776400000,
      "price": 114.69
    },
    {
      "x": 1686780000000,
      "price": 114.21
    },
    {
      "x": 1686783600000,
      "price": 105.0
    }
  ]
}