{
  "date": "2023-03-03",
  "market": "OMIE Portugal day-ahead",
  "rows": [
    {
      "x": 1677801600000,
      "price": 147.56
    },
    {
      "x": 1677805200000,
      "price": 145.79
    },
    {
      "x": 1677808800000,
      "price": 143.54
    },
    {
      "x": 1677812400000,
      "price": 143.11
    },
    {
      "x": 1677816000000,
      "price": 143.62
    },
    {
      "x": 1677819600000,
      "price": 146.37
    },
    {
      "x": 1677823200000,
      "price": 152.86
    },
    {
      "x": 1677826800000,
      "price": 156.99
    },
    {
      "x": 1677830400000,
      "price": 157.0
    },
    {
      "x": 1677834000000,
      "price": 149.13
    },
    {
      "x": 1677837600000,
      "price": 119.37
    },
    {
      "x": 1677841200000,
      "price": 119.44
    },
    {
      "x": 1677844800000,
      "price": 118.0
    },
    {
      "x": 1677848400000,
      "price": 117.5
    },
    {
      "x": 1677852000000,
      "price": 115.5
    },
    {
      "x": 1677855600000,
      "price": 115.5
    },
    {
      "x": 1677859200000,
      "price": 120.19
    },
    {
      "x": 1677862800000,
      "price": 143.84
    },
    {
      "x": 1677866400000,
      "price": 157.0
    },
    {
      "x": 1677870000000,
      "price": 163.24
    },
    {
      "x": 1677873600000,
      "price": 169.0
    },
    {
      "x": 1677877200000,
      "price": 163.0
    },
    {
      "x": 1677880800000,
      "price": 158.02
    },
    {
      "x": 1677884400000,
      "price": 155.76
    }
  ]
}