{
  "date": "2023-06-02",
  "market": "OMIE Portugal day-ahead",
  "rows": [
    {
      "x": 1685664000000,
      "price": 89.51
    },
    {
      "x": 1685667600000,
      "price": 80.1
    },
    {
      "x": 1685671200000,
      "price": 77.0
    },
    {
      "x": 1685674800000,
      "price": 77.0
    },
    {
      "x": 1685678400000,
      "price": 74.26
    },
    {
      "x": 1685682000000,
      "price": 80.0
    },
    {
      "x": 1685685600000,
      "price": 89.33
    },
    {
      "x": 1685689200000,
      "price": 91.72
    },
    {
      "x": 1685692800000,
      "price": 93.3
    },
    {
      "x": 1685696400000,
      "price": 87.44
    },
    {
      "x": 1685700000000,
      "price": 89.82
    },
    {
      "x": 1685703600000,
      "price": 82.1
    },
    {
      "x": 1685707200000,
      "price": 81.1
    },
    {
      "x": 1685710800000,
      "price": 81.1
    },
    {
      "x": 1685714400000,
      "price": 77.23
    },
    {
      "x": 1685718000000,
      "price": 77.07
    },
    {
      "x": 1685721600000,
      "price": 80.82
    },
    {
      "x": 1685725200000,
      "price": 88.0
    },
    {
      "x": 1685728800000,
      "price": 85.8
    },
    {
      "x": 1685732400000,
      "price": 91.4
    },
    {
      "x": 1685736000000,
      "price": 99.82
    },
    {
      "x": 1685739600000,
      "price": 103.53
    },
    {
      "x": 1685743200000,
      "price": 103.11
    },
    {
      "x": 1685746800000,
      "price": 101.09
    }
  ]
}