{
  "date": "2024-01-27",
  "market": "OMIE Portugal day-ahead",
  "rows": [
    {
      "x": 1706313600000,
      "price": 64.97
    },
    {
      "x": 1706317200000,
      "price": 61.06
    },
    {
      "x": 1706320800000,
      "price": 59.05
    },
    {
      "x": 1706324400000,
      "price": 55.9
    },
    {
      "x": 1706328000000,
      "price": 55.9
    },
    {
      "x": 1706331600000,
      "price": 57.22
    },
    {
      "x": 1706335200000,
      "price": 59.36
    },
    {
      "x": 1706338800000,
      "price": 66.19
    },
    {
      "x": 1706342400000,
      "price": 78.09
    },
    {
      "x": 1706346000000,
      "price": 73.4
    },
    {
      "x": 1706349600000,
      "price": 62.01
    },
    {
      "x": 1706353200000,
      "price": 54.4
    },
    {
      "x": 1706356800000,
      "price": 47.0
    },
    {
      "x": 1706360400000,
      "price": 47.7
    },
    {
      "x": 1706364000000,
      "price": 47.5
    },
    {
      "x": 1706367600000,
      "price": 47.0
    },
    {
      "x": 1706371200000,
      "price": 55.2
    },
    {
      "x": 1706374800000,
      "price": 74.43
    },
    {
      "x": 1706378400000,
      "price": 95.97
    },
    {
      "x": 1706382000000,
      "price": 92.51
    },
    {
      "x": 1706385600000,
      "price": 92.53
    },
    {
      "x": 1706389200000,
      "price": 89.5
    },
    {
      "x": 1706392800000,
      "price": 75.97
    },
    {
      "x": 1706396400000,
      "price": 72.7
    }
  ]
}