{
  "date": "2024-11-02",
  "market": "OMIE Portugal day-ahead",
  "rows": [
    {
      "x": 1730505600000,
      "price": 96.28
    },
    {
      "x": 1730509200000,
      "price": 91.56
    },
    {
      "x": 1730512800000,
      "price": 88.93
    },
    {
      "x": 1730516400000,
      "price": 86.0
    },
    {
      "x": 1730520000000,
      "price": 86.85
    },
    {
      "x": 1730523600000,
      "price": 85.62
    },
    {
      "x": 1730527200000,
      "price": 93.14
    },
    {
      "x": 1730530800000,
      "price": 100.11
    },
    {
      "x": 1730534400000,
      "price": 101.16
    },
    {
      "x": 1730538000000,
      "price": 88.93
    },
    {
      "x": 1730541600000,
      "price": 77.89
    },
    {
      "x": 1730545200000,
      "price": 71.77
    },
    {
      "x": 1730548800000,
      "price": 74.63
    },
    {
      "x": 1730552400000,
      "price": 69.84
    },
    {
      "x": 1730556000000,
      "price": 72.34
    },
    {
      "x": 1730559600000,
      "price": 70.63
    },
    {
      "x": 1730563200000,
      "price": 85.0
    },
    {
      "x": 1730566800000,
      "price": 105.82
    },
    {
      "x": 1730570400000,
      "price": 114.64
    },
    {
      "x": 1730574000000,
      "price": 114.64
    },
    {
      "x": 1730577600000,
      "price": 112.46
    },
    {
      "x": 1730581200000,
      "price": 111.54
    },
    {
      "x": 1730584800000,
      "price": 106.28
    },
    {
      "x": 1730588400000,
      "price": 100.61
    }
  ]
}