{
  "date": "2025-07-14",
  "market": "OMIE Portugal day-ahead",
  "rows": [
    {
      "x": 1752451200000,
      "price": 118.1
    },
    {
      "x": 1752454800000,
      "price": 112.45
    },
    {
      "x": 1752458400000,
      "price": 109.86
    },
    {
      "x": 1752462000000,
      "price": 109.23
    },
    {
      "x": 1752465600000,
      "price": 108.9
    },
    {
      "x": 1752469200000,
      "price": 110.1
    },
    {
      "x": 1752472800000,
      "price": 118.06
    },
    {
      "x": 1752476400000,
      "price": 122.72
    },
    {
      "x": 1752480000000,
      "price": 116.0
    },
    {
      "x": 1752483600000,
      "price": 75.19
    },
    {
      "x": 1752487200000,
      "price": 65.0
    },
    {
      "x": 1752490800000,
      "price": 33.72
    },
    {
      "x": 1752494400000,
      "price": 34.06
    },
    {
      "x": 1752498000000,
      "price": 38.8
    },
    {
      "x": 1752501600000,
      "price": 31.49
    },
    {
      "x": 1752505200000,
      "price": 18.21
    },
    {
      "x": 1752508800000,
      "price": 27.09
    },
    {
      "x": 1752512400000,
      "price": 47.5
    },
    {
      "x": 1752516000000,
      "price": 60.0
    },
    {
      "x": 1752519600000,
      "price": 77.76
    },
    {
      "x": 1752523200000,
      "price": 117.06
    },
    {
      "x": 1752526800000,
      "price": 126.64
    },
    {
      "x": 1752530400000,
      "price": 124.68
    },
    {
      "x": 1752534000000,
      "price": 118.26
    }
  ]
}