{
  "date": "2025-06-14",
  "market": "OMIE Portugal day-ahead",
  "rows": [
    {
      "x": 1749859200000,
      "price": 110.02
    },
    {
      "x": 1749862800000,
      "price": 109.7
    },
    {
      "x": 1749866400000,
      "price": 109.8
    },
    {
      "x": 1749870000000,
      "price": 108.98
    },
    {
      "x": 1749873600000,
      "price": 109.0
    },
    {
      "x": 1749877200000,
      "price": 109.7
    },
    {
      "x": 1749880800000,
      "price": 109.73
    },
    {
      "x": 1749884400000,
      "price": 104.9
    },
    {
      "x": 1749888000000,
      "price": 51.21
    },
    {
      "x": 1749891600000,
      "price": 4.17
    },
    {
      "x": 1749895200000,
      "price": 0.46
    },
    {
      "x": 1749898800000,
      "price": -0.01
    },
    {
      "x": 1749902400000,
      "price": -0.58
    },
    {
      "x": 1749906000000,
      "price": -0.62
    },
    {
      "x": 1749909600000,
      "price": -1.0
    },
    {
      "x": 1749913200000,
      "price": -1.5
    },
    {
      "x": 1749916800000,
      "price": -0.37
    },
    {
      "x": 1749920400000,
      "price": 0.65
    },
    {
      "x": 1749924000000,
      "price": 5.0
    },
    {
      "x": 1749927600000,
      "price": 36.27
    },
    {
      "x": 1749931200000,
      "price": 86.0
    },
    {
      "x": 1749934800000,
      "price": 101.96
    },
    {
      "x": 1749938400000,
      "price": 105.88
    },
    {
      "x": 1749942000000,
      "price": 100.98
    }
  ]
}