{
  "date": "2025-05-17",
  "market": "OMIE Portugal day-ahead",
  "rows": [
    {
      "x": 1747440000000,
      "price": 21.23
    },
    {
      "x": 1747443600000,
      "price": 13.53
    },
    {
      "x": 1747447200000,
      "price": 12.68
    },
    {
      "x": 1747450800000,
      "price": 14.26
    },
    {
      "x": 1747454400000,
      "price": 12.82
    },
    {
      "x": 1747458000000,
      "price": 19.0
    },
    {
      "x": 1747461600000,
      "price": 21.79
    },
    {
      "x": 1747465200000,
      "price": 20.23
    },
    {
      "x": 1747468800000,
      "price": 6.09
    },
    {
      "x": 1747472400000,
      "price": -0.01
    },
    {
      "x": 1747476000000,
      "price": -3.0
    },
    {
      "x": 1747479600000,
      "price": -5.7
    },
    {
      "x": 1747483200000,
      "price": -9.7
    },
    {
      "x": 1747486800000,
      "price": -10.01
    },
    {
      "x": 1747490400000,
      "price": -11.26
    },
    {
      "x": 1747494000000,
      "price": -10.0
    },
    {
      "x": 1747497600000,
      "price": -10.0
    },
    {
      "x": 1747501200000,
      "price": -5.8
    },
    {
      "x": 1747504800000,
      "price": -1.81
    },
    {
      "x": 1747508400000,
      "price": 3.52
    },
    {
      "x": 1747512000000,
      "price": 26.56
    },
    {
      "x": 1747515600000,
      "price": 52.5
    },
    {
      "x": 1747519200000,
      "price": 57.12
    },
    {
      "x": 1747522800000,
      "price": 41.28
    }
  ]
}