{
  "date": "2025-12-03",
  "market": "OMIE Portugal day-ahead",
  "rows": [
    {
      "x": 1764720000000,
      "price": 92.07
    },
    {
      "x": 1764723600000,
      "price": 88.98
    },
    {
      "x": 1764727200000,
      "price": 80.4
    },
    {
      "x": 1764730800000,
      "price": 78.74
    },
    {
      "x": 1764734400000,
      "price": 81.21
    },
    {
      "x": 1764738000000,
      "price": 78.74
    },
    {
      "x": 1764741600000,
      "price": 78.74
    },
    {
      "x": 1764745200000,
      "price": 78.74
    },
    {
      "x": 1764748800000,
      "price": 78.74
    },
    {
      "x": 1764752400000,
      "price": 76.36
    },
    {
      "x": 1764756000000,
      "price": 72.47
    },
    {
      "x": 1764759600000,
      "price": 70.5
    },
    {
      "x": 1764763200000,
      "price": 70.27
    },
    {
      "x": 1764766800000,
      "price": 67.72
    },
    {
      "x": 1764770400000,
      "price": 67.37
    },
    {
      "x": 1764774000000,
      "price": 67.24
    },
    {
      "x": 1764777600000,
      "price": 67.24
    },
    {
      "x": 1764781200000,
      "price": 66.98
    },
    {
      "x": 1764784800000,
      "price": 67.11
    },
    {
      "x": 1764788400000,
      "price": 67.24
    },
    {
      "x": 1764792000000,
      "price": 70.15
    },
    {
      "x": 1764795600000,
      "price": 71.2
    },
    {
      "x": 1764799200000,
      "price": 72.47
    },
    {
      "x": 1764802800000,
      "price": 75.1
    },
    {
      "x": 1764806400000,
      "price": 71.34
    },
    {
      "x": 1764742500000,
      "price": 76.56
    },
    {
      "x": 1764743400000,
      "price": 80.4
    },
    {
      "x": 1764744300000,
      "price": 83.3
    },
    {
      "x": 1764745200000,
      "price": 85.4
    },
    {
      "x": 1764746100000,
      "price": 95.0
    },
    {
      "x": 1764747000000,
      "price": 95.58
    },
    {
      "x": 1764747900000,
      "price": 96.3
    },
    {
      "x": 1764748800000,
      "price": 103.43
    },
    {
      "x": 1764749700000,
      "price": 100.86
    },
    {
      "x": 1764750600000,
      "price": 98.53
    },
    {
      "x": 1764751500000,
      "price": 96.54
    },
    {
      "x": 1764752400000,
      "price": 96.4
    },
    {
      "x": 1764753300000,
      "price": 93.3
    },
    {
      "x": 1764754200000,
      "price": 78.74
    },
    {
      "x": 1764755100000,
      "price": 67.07
    },
    {
      "x": 1764756000000,
      "price": 77.5
    },
    {
      "x": 1764756900000,
      "price": 70.82
    },
    {
      "x": 1764757800000,
      "price": 65.0
    },
    {
      "x": 1764758700000,
      "price": 56.2
    },
    {
      "x": 1764759600000,
      "price": 50.0
    },
    {
      "x": 1764760500000,
      "price": 40.0
    },
    {
      "x": 1764761400000,
      "price": 35.0
    },
    {
      "x": 1764762300000,
      "price": 27.55
    },
    {
      "x": 1764763200000,
      "price": 25.54
    },
    {
      "x": 1764764100000,
      "price": 20.0
    },
    {
      "x": 1764765000000,
      "price": 20.0
    },
    {
      "x": 1764765900000,
      "price": 16.99
    },
    {
      "x": 1764766800000,
      "price": 16.57
    },
    {
      "x": 1764767700000,
      "price": 16.2
    },
    {
      "x": 1764768600000,
      "price": 15.0
    },
    {
      "x": 1764769500000,
      "price": 14.0
    },
    {
      "x": 1764770400000,
      "price": 14.0
    },
    {
      "x": 1764771300000,
      "price": 14.0
    },
    {
      "x": 1764772200000,
      "price": 15.0
    },
    {
      "x": 1764773100000,
      "price": 15.35
    },
    {
      "x": 1764774000000,
      "price": 16.68
    },
    {
      "x": 1764774900000,
      "price": 21.6
    },
    {
      "x": 1764775800000,
      "price": 36.17
    },
    {
      "x": 1764776700000,
      "price": 50.0
    },
    {
      "x": 1764777600000,
      "price": 40.56
    },
    {
      "x": 1764778500000,
      "price": 65.9
    },
    {
      "x": 1764779400000,
      "price": 70.82
    },
    {
      "x": 1764780300000,
      "price": 80.61
    },
    {
      "x": 1764781200000,
      "price": 76.36
    },
    {
      "x": 1764782100000,
      "price": 85.05
    },
    {
      "x": 1764783000000,
      "price": 95.34
    },
    {
      "x": 1764783900000,
      "price": 96.4
    },
    {
      "x": 1764784800000,
      "price": 96.54
    },
    {
      "x": 1764785700000,
      "price": 98.53
    },
    {
      "x": 1764786600000,
      "price": 104.75
    },
    {
      "x": 1764787500000,
      "price": 109.92
    },
    {
      "x": 1764788400000,
      "price": 98.39
    },
    {
      "x": 1764789300000,
      "price": 100.0
    },
    {
      "x": 1764790200000,
      "price": 100.09
    },
    {
      "x": 1764791100000,
      "price": 98.39
    },
    {
      "x": 1764792000000,
      "price": 98.39
    },
    {
      "x": 1764792900000,
      "price": 97.98
    },
    {
      "x": 1764793800000,
      "price": 96.06
    },
    {
      "x": 1764794700000,
      "price": 95.1
    },
    {
      "x": 1764795600000,
      "price": 93.3
    },
    {
      "x": 1764796500000,
      "price": 93.3
    },
    {
      "x": 1764797400000,
      "price": 87.0
    },
    {
      "x": 1764798300000,
      "price": 81.44
    },
    {
      "x": 1764799200000,
      "price": 90.0
    },
    {
      "x": 1764800100000,
      "price": 86.55
    },
    {
      "x": 1764801000000,
      "price": 85.0
    },
    {
      "x": 1764801900000,
      "price": 80.35
    },
    {
      "x": 1764802800000,
      "price": 84.84
    },
    {
      "x": 1764803700000,
      "price": 78.74
    },
    {
      "x": 1764804600000,
      "price": 75.34
    },
    {
      "x": 1764805500000,
      "price": 65.26
    }
  ]
}